geo21/__init__.py
geo21-1.0.0.dist-info/LICENSE
geo21-1.0.0.dist-info/METADATA
geo21-1.0.0.dist-info/WHEEL
geo21-1.0.0.dist-info/top_level.txt
geo21-1.0.0.dist-info/RECORD
