Metadata-Version: 2.1
Name: geo21
Version: 1.0.0
Summary: It perform all the geoprocessing task
Home-page: UNKNOWN
Author: Nandan Pattanayak
Author-email: mail2nandan18@gmail.com
License: MIT
Platform: UNKNOWN
Classifier: License :: OSI Approved :: MIT License
Classifier: Programming Language :: Python :: 3.0
Classifier: Programming Language :: Python :: 3.6
Classifier: Programming Language :: Python :: 3.7
Classifier: Programming Language :: Python :: 3.8
License-File: LICENSE
Requires-Dist: pandas
Requires-Dist: numpy
Requires-Dist: Shapely
